dataframe_data_validation/__init__.py
dataframe_data_validation/validation.py
dataframe_data_validation-0.1.1.dist-info/METADATA
dataframe_data_validation-0.1.1.dist-info/WHEEL
dataframe_data_validation-0.1.1.dist-info/top_level.txt
dataframe_data_validation-0.1.1.dist-info/RECORD
